{"cameraMode":{"drawMode":0,"name":"Shaded","section":"Shading Mode"},"sceneLighting":true,"audioPlay":false,"sceneViewState":{"showFog":true,"showMaterialUpdate":false,"showSkybox":true,"showFlares":true,"showImageEffects":true,"showParticleSystems":true,"showVisualEffectGraphs":true,"m_FxEnabled":true},"in2DMode":false,"pivot":{"x":7.641334533691406,"y":4.59466552734375,"z":39.685157775878909},"rotation":{"x":0.33898764848709109,"y":0.3674837648868561,"z":-0.14592617750167848,"w":0.8536677956581116},"size":30.777183532714845,"orthographic":true}